{
  "updated": "2026-06-17T22:16:21.234078+00:00",
  "sectors": {
    "COM": {
      "name": "Communication Services",
      "above_20d": 22.2
    },
    "CND": {
      "name": "Consumer Discretionary",
      "above_20d": 55.0
    },
    "CNS": {
      "name": "Consumer Staples",
      "above_20d": 25.0
    },
    "ENE": {
      "name": "Energy",
      "above_20d": 0.0
    },
    "FIN": {
      "name": "Financials",
      "above_20d": 84.2
    },
    "HLC": {
      "name": "Health Care",
      "above_20d": 45.0
    },
    "IND": {
      "name": "Industrials",
      "above_20d": 65.0
    },
    "MAT": {
      "name": "Materials",
      "above_20d": 75.0
    },
    "RLE": {
      "name": "Real Estate",
      "above_20d": 26.3
    },
    "TEC": {
      "name": "Technology",
      "above_20d": 30.0
    },
    "UTL": {
      "name": "Utilities",
      "above_20d": 50.0
    }
  },
  "indices": {
    "SPX": {
      "20d": 43.9,
      "50d": 47.2,
      "100d": 50.0,
      "200d": 66.4
    },
    "NDX": {
      "20d": 40.0,
      "50d": 54.0,
      "100d": 62.0,
      "200d": 64.0
    },
    "DJI": {
      "20d": 55.2,
      "50d": 72.4,
      "100d": 58.6,
      "200d": 75.9
    },
    "RUT": {
      "20d": 43.9,
      "50d": 47.2,
      "100d": 50.0,
      "200d": 66.4
    },
    "VTI": {
      "20d": 43.9,
      "50d": 47.2,
      "100d": 50.0,
      "200d": 66.4
    }
  },
  "total": {
    "stacked": 477.7,
    "average": 43.4
  }
}