{
  "updated": "2026-03-27T03:58:58.760743",
  "quotes": [
    {
      "symbol": "ES=F",
      "label": "S&P 500",
      "group": "indices",
      "price": 6548.0,
      "change": 23.0,
      "changePct": 0.35,
      "prevClose": 6525.0
    },
    {
      "symbol": "NQ=F",
      "label": "Nasdaq",
      "group": "indices",
      "price": 23884.25,
      "change": 90.0,
      "changePct": 0.38,
      "prevClose": 23794.25
    },
    {
      "symbol": "RTY=F",
      "label": "Russell",
      "group": "indices",
      "price": 2519.4,
      "change": 11.2,
      "changePct": 0.45,
      "prevClose": 2508.2
    },
    {
      "symbol": "YM=F",
      "label": "Dow",
      "group": "indices",
      "price": 46360.0,
      "change": 130.0,
      "changePct": 0.28,
      "prevClose": 46230.0
    },
    {
      "symbol": "CL=F",
      "label": "Crude",
      "group": "commodities",
      "price": 95.1,
      "change": 0.62,
      "changePct": 0.66,
      "prevClose": 94.48
    },
    {
      "symbol": "NG=F",
      "label": "Nat Gas",
      "group": "commodities",
      "price": 2.97,
      "change": -0.03,
      "changePct": -0.9,
      "prevClose": 3.0
    },
    {
      "symbol": "GC=F",
      "label": "Gold",
      "group": "commodities",
      "price": 4478.8,
      "change": 103.3,
      "changePct": 2.36,
      "prevClose": 4375.5
    },
    {
      "symbol": "SI=F",
      "label": "Silver",
      "group": "commodities",
      "price": 69.75,
      "change": 2.08,
      "changePct": 3.08,
      "prevClose": 67.67
    },
    {
      "symbol": "HG=F",
      "label": "Copper",
      "group": "commodities",
      "price": 5.51,
      "change": 0.07,
      "changePct": 1.23,
      "prevClose": 5.45
    },
    {
      "symbol": "^TNX",
      "label": "US10Y",
      "group": "rates",
      "price": 4.42,
      "change": 0.09,
      "changePct": 2.03,
      "prevClose": 4.33
    },
    {
      "symbol": "DX-Y.NYB",
      "label": "DXY",
      "group": "rates",
      "price": 99.97,
      "change": 0.07,
      "changePct": 0.07,
      "prevClose": 99.9
    },
    {
      "symbol": "^VIX",
      "label": "VIX",
      "group": "volatility",
      "price": 27.65,
      "change": 0.21,
      "changePct": 0.77,
      "prevClose": 27.44
    },
    {
      "symbol": "BTC-USD",
      "label": "BTC",
      "group": "crypto",
      "price": 68529.92,
      "change": -261.71,
      "changePct": -0.38,
      "prevClose": 68791.62
    },
    {
      "symbol": "ETH-USD",
      "label": "ETH",
      "group": "crypto",
      "price": 2067.93,
      "change": 8.35,
      "changePct": 0.41,
      "prevClose": 2059.58
    }
  ]
}