{
  "updated": "2026-05-28T17:28:37.676660+00:00",
  "source": "yfinance",
  "tickers": {
    "AA": {
      "price": 74.9,
      "change": 2.39,
      "updated": "2026-05-28T17:28:37.676660+00:00"
    },
    "AAPL": {
      "price": 310.9,
      "change": 0.02,
      "updated": "2026-05-28T17:28:37.676660+00:00"
    },
    "ABBV": {
      "price": 219.01,
      "change": 1.68,
      "updated": "2026-05-28T17:28:37.676660+00:00"
    },
    "ACI": {
      "price": 15.92,
      "change": -0.69,
      "updated": "2026-05-28T17:28:37.676660+00:00"
    },
    "ADM": {
      "price": 80.28,
      "change": 0.92,
      "updated": "2026-05-28T17:28:37.676660+00:00"
    },
    "ADSK": {
      "price": 242.86,
      "change": 2.47,
      "updated": "2026-05-28T17:28:37.676660+00:00"
    },
    "AMZN": {
      "price": 271.38,
      "change": -0.17,
      "updated": "2026-05-28T17:28:37.676660+00:00"
    },
    "AR": {
      "price": 36.01,
      "change": 2.56,
      "updated": "2026-05-28T17:28:37.676660+00:00"
    },
    "ARM": {
      "price": 343.61,
      "change": 13.51,
      "updated": "2026-05-28T17:28:37.676660+00:00"
    },
    "AVGO": {
      "price": 428.1,
      "change": 1.48,
      "updated": "2026-05-28T17:28:37.676660+00:00"
    },
    "AWK": {
      "price": 124.04,
      "change": 0.21,
      "updated": "2026-05-28T17:28:37.676660+00:00"
    },
    "BE": {
      "price": 301.49,
      "change": 2.62,
      "updated": "2026-05-28T17:28:37.676660+00:00"
    },
    "BILI": {
      "price": 17.28,
      "change": -1.65,
      "updated": "2026-05-28T17:28:37.676660+00:00"
    },
    "BJ": {
      "price": 86.54,
      "change": 2.78,
      "updated": "2026-05-28T17:28:37.676660+00:00"
    },
    "BRK-B": {
      "price": 478.75,
      "change": -0.24,
      "updated": "2026-05-28T17:28:37.676660+00:00"
    },
    "BTC-USD": {
      "price": 73272.99,
      "change": -1.44,
      "updated": "2026-05-28T17:28:37.676660+00:00"
    },
    "BYD": {
      "price": 83.15,
      "change": 1.13,
      "updated": "2026-05-28T17:28:37.676660+00:00"
    },
    "CAG": {
      "price": 13.51,
      "change": 1.35,
      "updated": "2026-05-28T17:28:37.676660+00:00"
    },
    "CHTR": {
      "price": 146.44,
      "change": -0.5,
      "updated": "2026-05-28T17:28:37.676660+00:00"
    },
    "CL=F": {
      "price": 88.91,
      "change": 0.26,
      "updated": "2026-05-28T17:28:37.676660+00:00"
    },
    "COIN": {
      "price": 179.76,
      "change": 3.44,
      "updated": "2026-05-28T17:28:37.676660+00:00"
    },
    "COPX": {
      "price": 88.07,
      "change": 2.3,
      "updated": "2026-05-28T17:28:37.676660+00:00"
    },
    "CP": {
      "price": 90.86,
      "change": -0.44,
      "updated": "2026-05-28T17:28:37.676660+00:00"
    },
    "CPER": {
      "price": 39.08,
      "change": 1.56,
      "updated": "2026-05-28T17:28:37.676660+00:00"
    },
    "CRWD": {
      "price": 675.72,
      "change": 4.7,
      "updated": "2026-05-28T17:28:37.676660+00:00"
    },
    "D": {
      "price": 67.97,
      "change": 1.15,
      "updated": "2026-05-28T17:28:37.676660+00:00"
    },
    "DELL": {
      "price": 324.47,
      "change": 6.27,
      "updated": "2026-05-28T17:28:37.676660+00:00"
    },
    "DHR": {
      "price": 179.88,
      "change": 3.9,
      "updated": "2026-05-28T17:28:37.676660+00:00"
    },
    "DIA": {
      "price": 506.76,
      "change": -0.02,
      "updated": "2026-05-28T17:28:37.676660+00:00"
    },
    "DX-Y.NYB": {
      "price": 98.98,
      "change": -0.23,
      "updated": "2026-05-28T17:28:37.676660+00:00"
    },
    "FXI": {
      "price": 34.97,
      "change": -0.99,
      "updated": "2026-05-28T17:28:37.676660+00:00"
    },
    "GKOS": {
      "price": 110.12,
      "change": 0.22,
      "updated": "2026-05-28T17:28:37.676660+00:00"
    },
    "GLD": {
      "price": 413.44,
      "change": 1.21,
      "updated": "2026-05-28T17:28:37.676660+00:00"
    },
    "GOOG": {
      "price": 385.99,
      "change": 0.3,
      "updated": "2026-05-28T17:28:37.676660+00:00"
    },
    "GOOGL": {
      "price": 390.12,
      "change": 0.33,
      "updated": "2026-05-28T17:28:37.676660+00:00"
    },
    "HYG": {
      "price": 80.22,
      "change": 0.11,
      "updated": "2026-05-28T17:28:37.676660+00:00"
    },
    "IBIT": {
      "price": 41.51,
      "change": -2.21,
      "updated": "2026-05-28T17:28:37.676660+00:00"
    },
    "IFF": {
      "price": 78.23,
      "change": 1.6,
      "updated": "2026-05-28T17:28:37.676660+00:00"
    },
    "IGV": {
      "price": 95.79,
      "change": 2.94,
      "updated": "2026-05-28T17:28:37.676660+00:00"
    },
    "IWD": {
      "price": 238.48,
      "change": 0.23,
      "updated": "2026-05-28T17:28:37.676660+00:00"
    },
    "IWF": {
      "price": 126.87,
      "change": 0.92,
      "updated": "2026-05-28T17:28:37.676660+00:00"
    },
    "IWM": {
      "price": 291.83,
      "change": 0.5,
      "updated": "2026-05-28T17:28:37.676660+00:00"
    },
    "KHC": {
      "price": 24.58,
      "change": 0.82,
      "updated": "2026-05-28T17:28:37.676660+00:00"
    },
    "KMB": {
      "price": 100.52,
      "change": 0.34,
      "updated": "2026-05-28T17:28:37.676660+00:00"
    },
    "LLY": {
      "price": 1120.52,
      "change": 3.47,
      "updated": "2026-05-28T17:28:37.676660+00:00"
    },
    "LQD": {
      "price": 109.21,
      "change": 0.26,
      "updated": "2026-05-28T17:28:37.676660+00:00"
    },
    "META": {
      "price": 631.42,
      "change": -0.6,
      "updated": "2026-05-28T17:28:37.676660+00:00"
    },
    "MOO": {
      "price": 80.54,
      "change": 0.11,
      "updated": "2026-05-28T17:28:37.676660+00:00"
    },
    "MOS": {
      "price": 24.05,
      "change": 1.39,
      "updated": "2026-05-28T17:28:37.676660+00:00"
    },
    "MSFT": {
      "price": 425.64,
      "change": 3.14,
      "updated": "2026-05-28T17:28:37.676660+00:00"
    },
    "MU": {
      "price": 937.05,
      "change": 0.93,
      "updated": "2026-05-28T17:28:37.676660+00:00"
    },
    "NBIS": {
      "price": 227.18,
      "change": 9.03,
      "updated": "2026-05-28T17:28:37.676660+00:00"
    },
    "NEE": {
      "price": 88.1,
      "change": 0.51,
      "updated": "2026-05-28T17:28:37.676660+00:00"
    },
    "NVDA": {
      "price": 213.24,
      "change": 0.3,
      "updated": "2026-05-28T17:28:37.676660+00:00"
    },
    "OIH": {
      "price": 420.4,
      "change": -1.21,
      "updated": "2026-05-28T17:28:37.676660+00:00"
    },
    "OMC": {
      "price": 73.76,
      "change": -1.46,
      "updated": "2026-05-28T17:28:37.676660+00:00"
    },
    "PFE": {
      "price": 26.11,
      "change": -0.38,
      "updated": "2026-05-28T17:28:37.676660+00:00"
    },
    "QQQ": {
      "price": 735.69,
      "change": 0.86,
      "updated": "2026-05-28T17:28:37.676660+00:00"
    },
    "ROKU": {
      "price": 130.24,
      "change": -1.27,
      "updated": "2026-05-28T17:28:37.676660+00:00"
    },
    "RSP": {
      "price": 208.64,
      "change": 0.55,
      "updated": "2026-05-28T17:28:37.676660+00:00"
    },
    "RVTY": {
      "price": 102.0,
      "change": 5.38,
      "updated": "2026-05-28T17:28:37.676660+00:00"
    },
    "S": {
      "price": 18.1,
      "change": 0.84,
      "updated": "2026-05-28T17:28:37.676660+00:00"
    },
    "SLV": {
      "price": 68.36,
      "change": 1.27,
      "updated": "2026-05-28T17:28:37.676660+00:00"
    },
    "SM": {
      "price": 31.03,
      "change": 1.31,
      "updated": "2026-05-28T17:28:37.676660+00:00"
    },
    "SMH": {
      "price": 601.89,
      "change": 1.07,
      "updated": "2026-05-28T17:28:37.676660+00:00"
    },
    "SPY": {
      "price": 754.32,
      "change": 0.51,
      "updated": "2026-05-28T17:28:37.676660+00:00"
    },
    "STO.AX": {
      "price": 7.85,
      "change": -0.51,
      "updated": "2026-05-28T17:28:37.676660+00:00"
    },
    "SYK": {
      "price": 306.3,
      "change": 0.12,
      "updated": "2026-05-28T17:28:37.676660+00:00"
    },
    "TAP": {
      "price": 40.97,
      "change": -2.15,
      "updated": "2026-05-28T17:28:37.676660+00:00"
    },
    "TGT": {
      "price": 129.5,
      "change": 0.91,
      "updated": "2026-05-28T17:28:37.676660+00:00"
    },
    "TLT": {
      "price": 85.6,
      "change": 0.35,
      "updated": "2026-05-28T17:28:37.676660+00:00"
    },
    "TMO": {
      "price": 485.83,
      "change": 6.49,
      "updated": "2026-05-28T17:28:37.676660+00:00"
    },
    "TMUS": {
      "price": 189.32,
      "change": -0.78,
      "updated": "2026-05-28T17:28:37.676660+00:00"
    },
    "TQQQ": {
      "price": 83.75,
      "change": 2.55,
      "updated": "2026-05-28T17:28:37.676660+00:00"
    },
    "TSLA": {
      "price": 441.67,
      "change": 0.3,
      "updated": "2026-05-28T17:28:37.676660+00:00"
    },
    "TSM": {
      "price": 422.94,
      "change": 0.05,
      "updated": "2026-05-28T17:28:37.676660+00:00"
    },
    "UNG": {
      "price": 11.85,
      "change": 5.99,
      "updated": "2026-05-28T17:28:37.676660+00:00"
    },
    "UNH": {
      "price": 384.09,
      "change": 0.02,
      "updated": "2026-05-28T17:28:37.676660+00:00"
    },
    "UNP": {
      "price": 268.91,
      "change": -3.75,
      "updated": "2026-05-28T17:28:37.676660+00:00"
    },
    "UPS": {
      "price": 106.61,
      "change": 2.05,
      "updated": "2026-05-28T17:28:37.676660+00:00"
    },
    "URA": {
      "price": 50.49,
      "change": 0.66,
      "updated": "2026-05-28T17:28:37.676660+00:00"
    },
    "USO": {
      "price": 130.5,
      "change": -0.4,
      "updated": "2026-05-28T17:28:37.676660+00:00"
    },
    "UUP": {
      "price": 27.71,
      "change": -0.14,
      "updated": "2026-05-28T17:28:37.676660+00:00"
    },
    "XHB": {
      "price": 102.75,
      "change": -0.54,
      "updated": "2026-05-28T17:28:37.676660+00:00"
    },
    "XLB": {
      "price": 51.36,
      "change": 0.35,
      "updated": "2026-05-28T17:28:37.676660+00:00"
    },
    "XLC": {
      "price": 116.42,
      "change": 0.14,
      "updated": "2026-05-28T17:28:37.676660+00:00"
    },
    "XLE": {
      "price": 57.04,
      "change": 0.09,
      "updated": "2026-05-28T17:28:37.676660+00:00"
    },
    "XLF": {
      "price": 51.21,
      "change": -0.41,
      "updated": "2026-05-28T17:28:37.676660+00:00"
    },
    "XLI": {
      "price": 174.24,
      "change": -0.03,
      "updated": "2026-05-28T17:28:37.676660+00:00"
    },
    "XLK": {
      "price": 187.15,
      "change": 1.47,
      "updated": "2026-05-28T17:28:37.676660+00:00"
    },
    "XLP": {
      "price": 84.61,
      "change": 0.04,
      "updated": "2026-05-28T17:28:37.676660+00:00"
    },
    "XLRE": {
      "price": 44.63,
      "change": -0.0,
      "updated": "2026-05-28T17:28:37.676660+00:00"
    },
    "XLU": {
      "price": 44.96,
      "change": -0.4,
      "updated": "2026-05-28T17:28:37.676660+00:00"
    },
    "XLV": {
      "price": 150.62,
      "change": 1.23,
      "updated": "2026-05-28T17:28:37.676660+00:00"
    },
    "XLY": {
      "price": 121.65,
      "change": 0.08,
      "updated": "2026-05-28T17:28:37.676660+00:00"
    },
    "XME": {
      "price": 125.93,
      "change": 2.46,
      "updated": "2026-05-28T17:28:37.676660+00:00"
    },
    "ZM": {
      "price": 100.27,
      "change": 0.31,
      "updated": "2026-05-28T17:28:37.676660+00:00"
    },
    "^AXJO": {
      "price": 8717.7,
      "change": 0.69,
      "updated": "2026-05-28T17:28:37.676660+00:00"
    },
    "^DJT": {
      "price": 21411.96,
      "change": -0.4,
      "updated": "2026-05-28T17:28:37.676660+00:00"
    },
    "^FVX": {
      "price": 4.15,
      "change": -0.65,
      "updated": "2026-05-28T17:28:37.676660+00:00"
    },
    "^GDAXI": {
      "price": 25092.25,
      "change": -0.34,
      "updated": "2026-05-28T17:28:37.676660+00:00"
    },
    "^GSPC": {
      "price": 7560.57,
      "change": 0.53,
      "updated": "2026-05-28T17:28:37.676660+00:00"
    },
    "^HSI": {
      "price": 25328.23,
      "change": -1.06,
      "updated": "2026-05-28T17:28:37.676660+00:00"
    },
    "^IRX": {
      "price": 3.59,
      "change": 0.14,
      "updated": "2026-05-28T17:28:37.676660+00:00"
    },
    "^KS11": {
      "price": 8228.7,
      "change": 2.25,
      "updated": "2026-05-28T17:28:37.676660+00:00"
    },
    "^MOVE": {
      "price": 70.9,
      "change": -5.4,
      "updated": "2026-05-28T17:28:37.676660+00:00"
    },
    "^TNX": {
      "price": 4.45,
      "change": -0.69,
      "updated": "2026-05-28T17:28:37.676660+00:00"
    },
    "^VIX": {
      "price": 15.84,
      "change": -2.76,
      "updated": "2026-05-28T17:28:37.676660+00:00"
    }
  }
}