{
  "updated": "2026-06-10T16:50:05.352204+00:00",
  "source": "yfinance",
  "tickers": {
    "AA": {
      "price": 66.55,
      "change": -8.09,
      "updated": "2026-06-10T16:50:05.352204+00:00"
    },
    "AAPL": {
      "price": 292.58,
      "change": 0.7,
      "updated": "2026-06-10T16:50:05.352204+00:00"
    },
    "ABBV": {
      "price": 225.77,
      "change": 0.16,
      "updated": "2026-06-10T16:50:05.352204+00:00"
    },
    "ACI": {
      "price": 15.5,
      "change": -1.02,
      "updated": "2026-06-10T16:50:05.352204+00:00"
    },
    "ADM": {
      "price": 82.17,
      "change": 2.56,
      "updated": "2026-06-10T16:50:05.352204+00:00"
    },
    "ADSK": {
      "price": 223.46,
      "change": -0.28,
      "updated": "2026-06-10T16:50:05.352204+00:00"
    },
    "AMZN": {
      "price": 238.82,
      "change": -2.2,
      "updated": "2026-06-10T16:50:05.352204+00:00"
    },
    "AR": {
      "price": 35.52,
      "change": 2.48,
      "updated": "2026-06-10T16:50:05.352204+00:00"
    },
    "ASTS": {
      "price": 89.29,
      "change": 0.65,
      "updated": "2026-06-10T16:50:05.352204+00:00"
    },
    "AVGO": {
      "price": 373.2,
      "change": -4.83,
      "updated": "2026-06-10T16:50:05.352204+00:00"
    },
    "AWK": {
      "price": 126.9,
      "change": 1.09,
      "updated": "2026-06-10T16:50:05.352204+00:00"
    },
    "BE": {
      "price": 231.79,
      "change": -10.72,
      "updated": "2026-06-10T16:50:05.352204+00:00"
    },
    "BILI": {
      "price": 18.52,
      "change": 5.17,
      "updated": "2026-06-10T16:50:05.352204+00:00"
    },
    "BJ": {
      "price": 92.35,
      "change": 3.1,
      "updated": "2026-06-10T16:50:05.352204+00:00"
    },
    "BRK-B": {
      "price": 488.42,
      "change": 0.13,
      "updated": "2026-06-10T16:50:05.352204+00:00"
    },
    "BTC-USD": {
      "price": 61936.12,
      "change": 0.47,
      "updated": "2026-06-10T16:50:05.352204+00:00"
    },
    "BYD": {
      "price": 86.71,
      "change": -1.21,
      "updated": "2026-06-10T16:50:05.352204+00:00"
    },
    "CAG": {
      "price": 13.37,
      "change": 1.75,
      "updated": "2026-06-10T16:50:05.352204+00:00"
    },
    "CHTR": {
      "price": 139.44,
      "change": 3.01,
      "updated": "2026-06-10T16:50:05.352204+00:00"
    },
    "CL=F": {
      "price": 91.0,
      "change": 3.17,
      "updated": "2026-06-10T16:50:05.352204+00:00"
    },
    "COIN": {
      "price": 156.3,
      "change": 0.51,
      "updated": "2026-06-10T16:50:05.352204+00:00"
    },
    "COPX": {
      "price": 78.06,
      "change": -2.6,
      "updated": "2026-06-10T16:50:05.352204+00:00"
    },
    "CP": {
      "price": 90.05,
      "change": -0.17,
      "updated": "2026-06-10T16:50:05.352204+00:00"
    },
    "CPER": {
      "price": 38.12,
      "change": -1.24,
      "updated": "2026-06-10T16:50:05.352204+00:00"
    },
    "CRWD": {
      "price": 653.53,
      "change": 1.33,
      "updated": "2026-06-10T16:50:05.352204+00:00"
    },
    "D": {
      "price": 66.64,
      "change": 0.59,
      "updated": "2026-06-10T16:50:05.352204+00:00"
    },
    "DELL": {
      "price": 382.36,
      "change": 0.15,
      "updated": "2026-06-10T16:50:05.352204+00:00"
    },
    "DHR": {
      "price": 185.66,
      "change": -1.46,
      "updated": "2026-06-10T16:50:05.352204+00:00"
    },
    "DIA": {
      "price": 503.36,
      "change": -1.19,
      "updated": "2026-06-10T16:50:05.352204+00:00"
    },
    "DX-Y.NYB": {
      "price": 99.86,
      "change": -0.05,
      "updated": "2026-06-10T16:50:05.352204+00:00"
    },
    "FLY": {
      "price": 33.38,
      "change": -0.19,
      "updated": "2026-06-10T16:50:05.352204+00:00"
    },
    "FXI": {
      "price": 34.89,
      "change": 0.58,
      "updated": "2026-06-10T16:50:05.352204+00:00"
    },
    "GKOS": {
      "price": 121.95,
      "change": -3.47,
      "updated": "2026-06-10T16:50:05.352204+00:00"
    },
    "GLD": {
      "price": 378.15,
      "change": -3.23,
      "updated": "2026-06-10T16:50:05.352204+00:00"
    },
    "GOOG": {
      "price": 355.5,
      "change": -1.87,
      "updated": "2026-06-10T16:50:05.352204+00:00"
    },
    "GOOGL": {
      "price": 357.7,
      "change": -1.8,
      "updated": "2026-06-10T16:50:05.352204+00:00"
    },
    "HYG": {
      "price": 79.5,
      "change": -0.15,
      "updated": "2026-06-10T16:50:05.352204+00:00"
    },
    "IBIT": {
      "price": 35.08,
      "change": -0.17,
      "updated": "2026-06-10T16:50:05.352204+00:00"
    },
    "IFF": {
      "price": 75.93,
      "change": 0.2,
      "updated": "2026-06-10T16:50:05.352204+00:00"
    },
    "IGV": {
      "price": 92.75,
      "change": -0.22,
      "updated": "2026-06-10T16:50:05.352204+00:00"
    },
    "IWD": {
      "price": 236.76,
      "change": -0.59,
      "updated": "2026-06-10T16:50:05.352204+00:00"
    },
    "IWF": {
      "price": 120.5,
      "change": -1.25,
      "updated": "2026-06-10T16:50:05.352204+00:00"
    },
    "IWM": {
      "price": 283.93,
      "change": -0.38,
      "updated": "2026-06-10T16:50:05.352204+00:00"
    },
    "KHC": {
      "price": 24.1,
      "change": 2.86,
      "updated": "2026-06-10T16:50:05.352204+00:00"
    },
    "KMB": {
      "price": 101.68,
      "change": 1.15,
      "updated": "2026-06-10T16:50:05.352204+00:00"
    },
    "LLY": {
      "price": 1142.96,
      "change": -0.15,
      "updated": "2026-06-10T16:50:05.352204+00:00"
    },
    "LQD": {
      "price": 108.25,
      "change": -0.15,
      "updated": "2026-06-10T16:50:05.352204+00:00"
    },
    "LUNR": {
      "price": 26.45,
      "change": -3.71,
      "updated": "2026-06-10T16:50:05.352204+00:00"
    },
    "META": {
      "price": 576.75,
      "change": -1.34,
      "updated": "2026-06-10T16:50:05.352204+00:00"
    },
    "MOO": {
      "price": 78.04,
      "change": 0.22,
      "updated": "2026-06-10T16:50:05.352204+00:00"
    },
    "MOS": {
      "price": 20.71,
      "change": -2.68,
      "updated": "2026-06-10T16:50:05.352204+00:00"
    },
    "MSFT": {
      "price": 402.83,
      "change": -0.14,
      "updated": "2026-06-10T16:50:05.352204+00:00"
    },
    "MU": {
      "price": 898.8,
      "change": -3.96,
      "updated": "2026-06-10T16:50:05.352204+00:00"
    },
    "NBIS": {
      "price": 216.59,
      "change": -1.6,
      "updated": "2026-06-10T16:50:05.352204+00:00"
    },
    "NEE": {
      "price": 85.1,
      "change": 0.32,
      "updated": "2026-06-10T16:50:05.352204+00:00"
    },
    "NVDA": {
      "price": 202.81,
      "change": -2.58,
      "updated": "2026-06-10T16:50:05.352204+00:00"
    },
    "OIH": {
      "price": 425.29,
      "change": 1.08,
      "updated": "2026-06-10T16:50:05.352204+00:00"
    },
    "OMC": {
      "price": 75.64,
      "change": 0.01,
      "updated": "2026-06-10T16:50:05.352204+00:00"
    },
    "PFE": {
      "price": 25.65,
      "change": -0.19,
      "updated": "2026-06-10T16:50:05.352204+00:00"
    },
    "PL": {
      "price": 30.57,
      "change": -1.92,
      "updated": "2026-06-10T16:50:05.352204+00:00"
    },
    "QQQ": {
      "price": 697.76,
      "change": -1.42,
      "updated": "2026-06-10T16:50:05.352204+00:00"
    },
    "RDW": {
      "price": 14.95,
      "change": -5.08,
      "updated": "2026-06-10T16:50:05.352204+00:00"
    },
    "RKLB": {
      "price": 106.89,
      "change": -1.24,
      "updated": "2026-06-10T16:50:05.352204+00:00"
    },
    "ROKU": {
      "price": 118.43,
      "change": -2.05,
      "updated": "2026-06-10T16:50:05.352204+00:00"
    },
    "RSP": {
      "price": 208.05,
      "change": -0.54,
      "updated": "2026-06-10T16:50:05.352204+00:00"
    },
    "RVTY": {
      "price": 103.26,
      "change": -0.84,
      "updated": "2026-06-10T16:50:05.352204+00:00"
    },
    "S": {
      "price": 15.05,
      "change": -1.25,
      "updated": "2026-06-10T16:50:05.352204+00:00"
    },
    "SLV": {
      "price": 58.61,
      "change": -0.68,
      "updated": "2026-06-10T16:50:05.352204+00:00"
    },
    "SM": {
      "price": 33.06,
      "change": 6.37,
      "updated": "2026-06-10T16:50:05.352204+00:00"
    },
    "SMH": {
      "price": 574.74,
      "change": -2.75,
      "updated": "2026-06-10T16:50:05.352204+00:00"
    },
    "SPY": {
      "price": 729.95,
      "change": -0.96,
      "updated": "2026-06-10T16:50:05.352204+00:00"
    },
    "STO.AX": {
      "price": 7.91,
      "change": 0.51,
      "updated": "2026-06-10T16:50:05.352204+00:00"
    },
    "SYK": {
      "price": 311.12,
      "change": -0.92,
      "updated": "2026-06-10T16:50:05.352204+00:00"
    },
    "TAP": {
      "price": 41.04,
      "change": 1.28,
      "updated": "2026-06-10T16:50:05.352204+00:00"
    },
    "TGT": {
      "price": 127.08,
      "change": 0.37,
      "updated": "2026-06-10T16:50:05.352204+00:00"
    },
    "TLT": {
      "price": 85.02,
      "change": -0.12,
      "updated": "2026-06-10T16:50:05.352204+00:00"
    },
    "TMO": {
      "price": 486.64,
      "change": -1.5,
      "updated": "2026-06-10T16:50:05.352204+00:00"
    },
    "TMUS": {
      "price": 184.2,
      "change": 2.64,
      "updated": "2026-06-10T16:50:05.352204+00:00"
    },
    "TQQQ": {
      "price": 70.53,
      "change": -4.33,
      "updated": "2026-06-10T16:50:05.352204+00:00"
    },
    "TSLA": {
      "price": 381.89,
      "change": -3.73,
      "updated": "2026-06-10T16:50:05.352204+00:00"
    },
    "TSM": {
      "price": 413.95,
      "change": -3.26,
      "updated": "2026-06-10T16:50:05.352204+00:00"
    },
    "UNG": {
      "price": 11.56,
      "change": 1.49,
      "updated": "2026-06-10T16:50:05.352204+00:00"
    },
    "UNH": {
      "price": 406.98,
      "change": -1.46,
      "updated": "2026-06-10T16:50:05.352204+00:00"
    },
    "UNP": {
      "price": 268.74,
      "change": -0.94,
      "updated": "2026-06-10T16:50:05.352204+00:00"
    },
    "UPS": {
      "price": 104.0,
      "change": -3.59,
      "updated": "2026-06-10T16:50:05.352204+00:00"
    },
    "URA": {
      "price": 42.79,
      "change": -3.01,
      "updated": "2026-06-10T16:50:05.352204+00:00"
    },
    "USO": {
      "price": 135.45,
      "change": 3.16,
      "updated": "2026-06-10T16:50:05.352204+00:00"
    },
    "UUP": {
      "price": 28.01,
      "change": -0.0,
      "updated": "2026-06-10T16:50:05.352204+00:00"
    },
    "XHB": {
      "price": 104.72,
      "change": -2.15,
      "updated": "2026-06-10T16:50:05.352204+00:00"
    },
    "XLB": {
      "price": 50.1,
      "change": -1.32,
      "updated": "2026-06-10T16:50:05.352204+00:00"
    },
    "XLC": {
      "price": 111.64,
      "change": 0.14,
      "updated": "2026-06-10T16:50:05.352204+00:00"
    },
    "XLE": {
      "price": 58.83,
      "change": 2.51,
      "updated": "2026-06-10T16:50:05.352204+00:00"
    },
    "XLF": {
      "price": 52.56,
      "change": 0.19,
      "updated": "2026-06-10T16:50:05.352204+00:00"
    },
    "XLI": {
      "price": 171.05,
      "change": -2.59,
      "updated": "2026-06-10T16:50:05.352204+00:00"
    },
    "XLK": {
      "price": 177.84,
      "change": -1.62,
      "updated": "2026-06-10T16:50:05.352204+00:00"
    },
    "XLP": {
      "price": 85.31,
      "change": 1.44,
      "updated": "2026-06-10T16:50:05.352204+00:00"
    },
    "XLRE": {
      "price": 45.17,
      "change": 0.44,
      "updated": "2026-06-10T16:50:05.352204+00:00"
    },
    "XLU": {
      "price": 44.12,
      "change": 0.32,
      "updated": "2026-06-10T16:50:05.352204+00:00"
    },
    "XLV": {
      "price": 153.6,
      "change": -0.63,
      "updated": "2026-06-10T16:50:05.352204+00:00"
    },
    "XLY": {
      "price": 113.92,
      "change": -1.68,
      "updated": "2026-06-10T16:50:05.352204+00:00"
    },
    "XME": {
      "price": 113.75,
      "change": -2.02,
      "updated": "2026-06-10T16:50:05.352204+00:00"
    },
    "ZM": {
      "price": 95.0,
      "change": -1.89,
      "updated": "2026-06-10T16:50:05.352204+00:00"
    },
    "^AXJO": {
      "price": 8604.2,
      "change": -0.24,
      "updated": "2026-06-10T16:50:05.352204+00:00"
    },
    "^DJT": {
      "price": 21934.37,
      "change": -2.19,
      "updated": "2026-06-10T16:50:05.352204+00:00"
    },
    "^FVX": {
      "price": 4.25,
      "change": -0.07,
      "updated": "2026-06-10T16:50:05.352204+00:00"
    },
    "^GDAXI": {
      "price": 24195.31,
      "change": -0.97,
      "updated": "2026-06-10T16:50:05.352204+00:00"
    },
    "^GSPC": {
      "price": 7312.9,
      "change": -1.0,
      "updated": "2026-06-10T16:50:05.352204+00:00"
    },
    "^HSI": {
      "price": 24565.9,
      "change": -0.37,
      "updated": "2026-06-10T16:50:05.352204+00:00"
    },
    "^IRX": {
      "price": 3.63,
      "change": -0.14,
      "updated": "2026-06-10T16:50:05.352204+00:00"
    },
    "^KS11": {
      "price": 8096.93,
      "change": 8.18,
      "updated": "2026-06-10T16:50:05.352204+00:00"
    },
    "^MOVE": {
      "price": 77.03,
      "change": 0.06,
      "updated": "2026-06-10T16:50:05.352204+00:00"
    },
    "^TNX": {
      "price": 4.53,
      "change": 0.04,
      "updated": "2026-06-10T16:50:05.352204+00:00"
    },
    "^VIX": {
      "price": 21.71,
      "change": 9.26,
      "updated": "2026-06-10T16:50:05.352204+00:00"
    }
  }
}