{
  "Energy": {
    "etf": "XLE",
    "quadrant": "Weakening",
    "risk": "elevated",
    "rs": 117.39,
    "momentum": 93.84
  },
  "Clean Energy": {
    "etf": "XLE",
    "quadrant": "Weakening",
    "risk": "elevated",
    "rs": 117.39,
    "momentum": 93.84
  },
  "Materials": {
    "etf": "XLB",
    "quadrant": "Weakening",
    "risk": "elevated",
    "rs": 104.97,
    "momentum": 95.28
  },
  "Agriculture": {
    "etf": "XLB",
    "quadrant": "Weakening",
    "risk": "elevated",
    "rs": 104.97,
    "momentum": 95.28
  },
  "Industrials": {
    "etf": "XLI",
    "quadrant": "Weakening",
    "risk": "elevated",
    "rs": 100.61,
    "momentum": 92.98
  },
  "Discretionary": {
    "etf": "XLY",
    "quadrant": "Improving",
    "risk": "elevated",
    "rs": 94.74,
    "momentum": 102.29
  },
  "Retail": {
    "etf": "XLY",
    "quadrant": "Improving",
    "risk": "elevated",
    "rs": 94.74,
    "momentum": 102.29
  },
  "Staples": {
    "etf": "XLP",
    "quadrant": "Lagging",
    "risk": "high",
    "rs": 98.04,
    "momentum": 92.08
  },
  "Healthcare": {
    "etf": "XLV",
    "quadrant": "Lagging",
    "risk": "high",
    "rs": 92.92,
    "momentum": 97.01
  },
  "Financials": {
    "etf": "XLF",
    "quadrant": "Improving",
    "risk": "elevated",
    "rs": 94.46,
    "momentum": 101.26
  },
  "Technology": {
    "etf": "XLK",
    "quadrant": "Leading",
    "risk": "low",
    "rs": 102.75,
    "momentum": 103.23
  },
  "Telecom": {
    "etf": "XLK",
    "quadrant": "Leading",
    "risk": "low",
    "rs": 102.75,
    "momentum": 103.23
  },
  "Semiconductors": {
    "etf": "XLK",
    "quadrant": "Leading",
    "risk": "low",
    "rs": 102.75,
    "momentum": 103.23
  },
  "Communication": {
    "etf": "XLC",
    "quadrant": "Leading",
    "risk": "low",
    "rs": 101.75,
    "momentum": 103.03
  },
  "Utilities": {
    "etf": "XLU",
    "quadrant": "Weakening",
    "risk": "elevated",
    "rs": 105.75,
    "momentum": 93.31
  },
  "Real Estate": {
    "etf": "XLRE",
    "quadrant": "Weakening",
    "risk": "elevated",
    "rs": 102.72,
    "momentum": 94.73
  },
  "Bond": {
    "etf": null,
    "quadrant": "N/A",
    "risk": "neutral",
    "rs": 100,
    "momentum": 100
  },
  "ETF": {
    "etf": null,
    "quadrant": "N/A",
    "risk": "neutral",
    "rs": 100,
    "momentum": 100
  },
  "Index": {
    "etf": null,
    "quadrant": "N/A",
    "risk": "neutral",
    "rs": 100,
    "momentum": 100
  },
  "Crypto": {
    "etf": null,
    "quadrant": "N/A",
    "risk": "neutral",
    "rs": 100,
    "momentum": 100
  }
}